binarysearchfile.py
binarysearchfile_tests.py
binarysearchfile-0.2.0.dist-info/METADATA
binarysearchfile-0.2.0.dist-info/WHEEL
binarysearchfile-0.2.0.dist-info/top_level.txt
binarysearchfile-0.2.0.dist-info/RECORD
