Metadata-Version: 2.1
Name: binarysearchfile
Version: 0.2.0
Summary: Binary search binary file for fast random access
Author: Tom Eulenfeld
License: MIT License
Project-URL: Homepage, https://github.com/trichter/binarysearchfile
Project-URL: Bug Tracker, https://github.com/trichter/binarysearchfile/issues
Keywords: binary search,random access,direct access
Classifier: Programming Language :: Python :: 3
Classifier: License :: OSI Approved :: MIT License
Classifier: Operating System :: OS Independent
